findrum/__init__.py
findrum/clients/client.py
findrum/clients/local_client.py
findrum/clients/minio_client.py
findrum/crawlers/crawler.py
findrum/crawlers/sec_crawler.py
findrum/crawlers/yahoo_crawler.py
findrum/readers/parquet_reader.py
findrum/readers/reader.py
findrum/writers/parquet_writer.py
findrum/writers/writer.py
findrum-1.0.5.dist-info/METADATA
findrum-1.0.5.dist-info/WHEEL
findrum-1.0.5.dist-info/top_level.txt
findrum-1.0.5.dist-info/RECORD
